fbchat/__init__.py
fbchat/_attachment.py
fbchat/_client.py
fbchat/_core.py
fbchat/_exception.py
fbchat/_file.py
fbchat/_graphql.py
fbchat/_group.py
fbchat/_location.py
fbchat/_message.py
fbchat/_mqtt.py
fbchat/_page.py
fbchat/_plan.py
fbchat/_poll.py
fbchat/_quick_reply.py
fbchat/_state.py
fbchat/_sticker.py
fbchat/_thread.py
fbchat/_user.py
fbchat/_util.py
fbchat/models.py
fbchat-1.9.6.dist-info/LICENSE
fbchat-1.9.6.dist-info/WHEEL
fbchat-1.9.6.dist-info/METADATA
fbchat-1.9.6.dist-info/RECORD
