Metadata-Version: 1.1
Name: fbchat
Version: 1.9.6
Summary: Facebook Chat (Messenger) for Python
Home-page: https://github.com/carpedm20/fbchat/
Author: Taehoon Kim
Author-email: carpedm20@gmail.com
